[
["Spikes", { "x": 805, "y": 1878 }],
["Spikes", { "x": 945, "y": 1878 }],
["SlimeGreen", { "x": 644, "y": 1995, "vx": 250 }],
["Spikes", { "x": 1785, "y": 1948 }],
["SlimeGreen", { "x": 2046, "y": 1995, "vx": -230 }],
["Slime", { "x": 2233, "y": 1855, "vx": 210 }],
["Slime", { "x": 3841, "y": 1995, "vx": 210 }],
["Slime", { "x": 4311, "y": 1995, "vx": -230 }],
["Slime", { "x": 4521, "y": 1995, "vx": 203 }],
["Spikes", { "x": 5775, "y": 1948 }],
["Spikes", { "x": 6051, "y": 1948 }],
["Spikes", { "x": 6335, "y": 1948 }],
["Door", { "x": 6700, "y": 1975 }]
]